README.md
setup.py
py_sa/__init__.py
py_sa/_version.py
py_sa/aegea_cmds/__init__.py
pysa_aws.egg-info/PKG-INFO
pysa_aws.egg-info/SOURCES.txt
pysa_aws.egg-info/dependency_links.txt
pysa_aws.egg-info/not-zip-safe
pysa_aws.egg-info/requires.txt
pysa_aws.egg-info/top_level.txt