Metadata-Version: 1.0
Name: pysa-aws
Version: 0.0.1
Summary: Interact with aegea and s3 through python
Home-page: UNKNOWN
Author: Matt Olm
Author-email: mattolm@stanford.edu
License: MIT
Platform: UNKNOWN
